ejtraderMT/__init__.py
ejtraderMT/api/__init__.py
ejtraderMT/api/mql.py
ejtraderMT-3.17.dist-info/LICENSE
ejtraderMT-3.17.dist-info/METADATA
ejtraderMT-3.17.dist-info/WHEEL
ejtraderMT-3.17.dist-info/top_level.txt
ejtraderMT-3.17.dist-info/RECORD
