Metadata-Version: 2.1
Name: ejtraderMT
Version: 3.17
Summary: Metatrader API
Home-page: https://ejtraderMT.readthedocs.io/
Download-URL: https://ejtrader.com
Author: Emerson Pedroso
Author-email: support@ejtrader.com
License: GPL-3.0
Project-URL: Bug Reports, https://github.com/traderpedroso/ejtraderMT/issues
Project-URL: Source, https://github.com/traderpedroso/ejtraderMT
Project-URL: Documentation, https://ejtrader.readthedocs.io/
Keywords: metatrader,f-api,historical-data,financial-data,stocks,funds,etfs,indices,currency crosses,bonds,commodities,crypto currencies
Classifier: Programming Language :: Python :: 3 :: Only
Classifier: Programming Language :: Python :: 3.5
Classifier: Programming Language :: Python :: 3.6
Classifier: Programming Language :: Python :: 3.7
Classifier: Programming Language :: Python :: 3.8
Classifier: Programming Language :: Python :: 3.9
Classifier: License :: OSI Approved :: MIT License
Classifier: Intended Audience :: Developers
Classifier: Topic :: Office/Business :: Financial
Classifier: Topic :: Office/Business :: Financial :: Investment
Classifier: Topic :: Scientific/Engineering :: Information Analysis
Classifier: Topic :: Software Development :: Libraries
Requires-Python: >=3
License-File: LICENSE
Requires-Dist: pandas (>=0.25.1)
Requires-Dist: pyzmq (==25.0.0)
Requires-Dist: tzlocal (==2.1)
Requires-Dist: ejtraderTH (==1.0.3)
Requires-Dist: ejtraderDB (==1.0.2)
Requires-Dist: tqdm (==4.56.0)
Requires-Dist: influxdb (==5.3.1)
